chatfactory/__init__.py
chatfactory/dialogue_generator.py
chatfactory/environment/__init__.py
chatfactory/environment/actions.py
chatfactory/environment/descriptions.py
chatfactory/environment/entities.py
chatfactory/environment/helpers.py
chatfactory/environments/__init__.py
chatfactory/environments/builders.py
chatfactory/environments/easy.py
chatfactory/environments/hard.py
chatfactory/environments/path_helpers.py
chatfactory/environments/world.py
chatfactory/generation/__init__.py
chatfactory/generation/dialogue.py
chatfactory/generation/file_list_db.py
chatfactory/generation/goal_generators.py
chatfactory/generation/helpers.py
chatfactory/generation/mappers_database.py
chatfactory/generation/param_generators.py
chatfactory/generation/templates.py
chatfactory/language/__init__.py
chatfactory/language/components.py
chatfactory/language/desc_mappers.py
chatfactory/language/describers.py
chatfactory/language/helpers.py
chatfactory/language/phrases.py
chatfactory/language/queries.py
chatfactory/language/sentences.py
chatfactory/language/words.py
chatfactory/policies/__init__.py
chatfactory/policies/agent_policies.py
chatfactory/policies/base_policies.py
chatfactory/policies/env_policies.py
chatfactory/policies/goals.py
chatfactory/policies/policies_helpers.py
chatfactory/policies/user_policies.py
chatfactory/state/__init__.py
chatfactory/state/kn_checkers.py
chatfactory/state/kn_helpers.py
chatfactory/state/kn_parsers.py
chatfactory/state/kn_updaters.py
chatfactory/state/knowledge_base.py
chatfactory/trainers/__init__.py
chatfactory/trainers/arch.py
chatfactory/trainers/baseline.py
chatfactory/trainers/evaluation.py
chatfactory/trainers/serializers.py
chatfactory/trainers/vocab.py
chatfactory-1.1.2.dist-info/METADATA
chatfactory-1.1.2.dist-info/WHEEL
chatfactory-1.1.2.dist-info/licenses/LICENSE.md
chatfactory-1.1.2.dist-info/RECORD
