Metadata-Version: 2.3
Name: chatfactory
Version: 1.1.2
Summary: Automatically generating dialogues grounded in a textual environment
Project-URL: Homepage, https://github.com/smartinovski/chatfactory
Project-URL: Issues, https://github.com/smartinovski/chatfactory/issues
Project-URL: Contribute, https://github.com/smartinovski/chatfactory#contribute
Project-URL: Support Us, https://github.com/smartinovski/chatfactory#support-us
Author-email: Stefan Martinovski <admin@revivegretel.com>
License-File: LICENSE.md
Classifier: License :: OSI Approved :: MIT License
Classifier: Operating System :: OS Independent
Classifier: Programming Language :: Python :: 3
Requires-Python: >=3.8
Requires-Dist: dijkstar
Requires-Dist: file-read-backwards
Requires-Dist: ipywidgets
Requires-Dist: notebook
Requires-Dist: pyinflect
Requires-Dist: spacy
Requires-Dist: tqdm
